banditopt/__init__.py
banditopt/algorithms.py
banditopt/decorr.py
banditopt/fsc.py
banditopt/microscope.py
banditopt/models.py
banditopt/objectives.py
banditopt/user.py
banditopt/utils.py
bandit_optimization-0.0.1.dist-info/LICENSE
bandit_optimization-0.0.1.dist-info/METADATA
bandit_optimization-0.0.1.dist-info/WHEEL
bandit_optimization-0.0.1.dist-info/top_level.txt
bandit_optimization-0.0.1.dist-info/RECORD
