Metadata-Version: 2.1
Name: bandit-optimization
Version: 0.0.1
Summary: Bandit optimization algorithms for microscopy
Author-email: Anthony Bilodeau <anthony.bilodeau.1@ulaval.ca>, Albert Michaud-Gagnon <albert.michaud-gagnon@cervo.ulaval.ca>
Maintainer-email: Anthony Bilodeau <anthony.bilodeau.1@ulaval.ca>
Project-URL: Homepage, https://github.com/FLClab/bandit-optimization
Project-URL: Issues, https://github.com/FLClab/bandit-optimization/issues
Keywords: microscopy,sted,bandit,optimization
Classifier: Programming Language :: Python :: 3
Classifier: License :: OSI Approved
Classifier: Operating System :: OS Independent
Requires-Python: >=3.8
License-File: LICENSE
Requires-Dist: pyyaml
Requires-Dist: matplotlib
Requires-Dist: statsmodels
Requires-Dist: deap >=1.3
Requires-Dist: scikit-learn
Requires-Dist: numpy
Requires-Dist: torch
Requires-Dist: tqdm
Requires-Dist: scikit-image
